automation/__init__.py
automation/api_tools.py
automation/cli.py
automation/file_tools.py
automation/github_tools.py
automation/linux_tools.py
automation/logger.py
automation/scheduler.py
automation/__pycache__/__init__.cpython-313.pyc
automation/__pycache__/api_tools.cpython-313.pyc
automation/__pycache__/cli.cpython-313.pyc
automation/__pycache__/file_tools.cpython-313.pyc
automation/__pycache__/github_tools.cpython-313.pyc
automation/__pycache__/linux_tools.cpython-313.pyc
automation/__pycache__/logger.cpython-313.pyc
automation/__pycache__/scheduler.cpython-313.pyc
python_automation_toolkit-2.0.0.dist-info/licenses/LICENCE
python_automation_toolkit-2.0.0.dist-info/licenses/LICENSE
python_automation_toolkit-2.0.0.dist-info/METADATA
python_automation_toolkit-2.0.0.dist-info/WHEEL
python_automation_toolkit-2.0.0.dist-info/entry_points.txt
python_automation_toolkit-2.0.0.dist-info/top_level.txt
python_automation_toolkit-2.0.0.dist-info/RECORD
